moffee/README.txt
moffee/__init__.py
moffee/builder.py
moffee/cli.py
moffee/compositor.py
moffee/markdown.py
moffee/templates/base/css/code-highlight.css
moffee/templates/base/css/extension.css
moffee/templates/base/css/styles.css
moffee/templates/base/index.html
moffee/templates/base/js/extension.js
moffee/templates/base/js/main.js
moffee/templates/base/layouts/centered.html
moffee/templates/base/layouts/content.html
moffee/templates/base/layouts/product.html
moffee/templates/beam/css/extension.css
moffee/templates/beam/layouts/centered.html
moffee/templates/beam/layouts/content.html
moffee/templates/blue/css/extension.css
moffee/templates/default/css/extension.css
moffee/templates/gaia/css/extension.css
moffee/templates/robo/css/extension.css
moffee/utils/file_helper.py
moffee/utils/math_escape_ext.py
moffee/utils/md_helper.py
moffee/utils/md_obsidian_ext.py
moffee-0.2.7.dist-info/LICENSE
moffee-0.2.7.dist-info/METADATA
moffee-0.2.7.dist-info/WHEEL
moffee-0.2.7.dist-info/entry_points.txt
moffee-0.2.7.dist-info/RECORD
