Metadata-Version: 2.1
Name: moffee
Version: 0.2.7
Summary: A slide maker that transform markdown into slides.
Home-page: https://github.com/bmpixel/moffee
License: MIT
Keywords: markdown,slides,presentation,CLI
Author: Wenbo Pan
Author-email: pixelwenbo@gmail.com
Requires-Python: >=3.10,<4.0
Classifier: License :: OSI Approved :: MIT License
Classifier: Programming Language :: Python :: 3
Classifier: Programming Language :: Python :: 3.10
Classifier: Programming Language :: Python :: 3.11
Classifier: Programming Language :: Python :: 3.12
Requires-Dist: beautifulsoup4 (>=4.12.3,<5.0.0)
Requires-Dist: click (>=8.1.7,<9.0.0)
Requires-Dist: jinja2 (>=3.1.4,<4.0.0)
Requires-Dist: livereload (>=2.7.0,<3.0.0)
Requires-Dist: markdown (>=3.6,<4.0)
Requires-Dist: myst-parser (>=4.0.0,<5.0.0)
Requires-Dist: pymdown-extensions (>=10.8.1,<11.0.0)
Requires-Dist: pyyaml (>=6.0.1,<7.0.0)
Project-URL: Repository, https://github.com/bmpixel/moffee
